buspyrate/__init__.py
buspyrate/py.typed
buspyrate-0.0.0.dist-info/LICENSE
buspyrate-0.0.0.dist-info/METADATA
buspyrate-0.0.0.dist-info/WHEEL
buspyrate-0.0.0.dist-info/top_level.txt
buspyrate-0.0.0.dist-info/RECORD
