Metadata-Version: 2.1
Name: buspyrate
Version: 0.0.0
Summary: BusPirate binary mode library
Home-page: https://gitlab.com/mpasternacki/buspyrate
Author: Maciej Pasternacki
Author-email: maciej@3ofcoins.net
License: bsd-2-clause
Platform: UNKNOWN
Classifier: Development Status :: 1 - Planning
Classifier: Intended Audience :: Developers
Classifier: License :: OSI Approved :: BSD License
Classifier: Programming Language :: Python :: 3
Classifier: Programming Language :: Python :: 3.9
Classifier: Topic :: Scientific/Engineering :: Interface Engine/Protocol Translator
Classifier: Topic :: Software Development :: Embedded Systems
Classifier: Typing :: Typed
Requires-Dist: pyserial
Provides-Extra: test
Requires-Dist: isort ; extra == 'test'
Requires-Dist: mypy ; extra == 'test'
Requires-Dist: pylama ; extra == 'test'
Requires-Dist: pytest ; extra == 'test'
Requires-Dist: pytest-cov ; extra == 'test'
Requires-Dist: pytest-mypy ; extra == 'test'
